google_maps_reviews/__init__.py
google_maps_reviews/client.py
google_maps_reviews/utils.py
google_maps_reviews-0.0.3.dist-info/LICENSE
google_maps_reviews-0.0.3.dist-info/METADATA
google_maps_reviews-0.0.3.dist-info/WHEEL
google_maps_reviews-0.0.3.dist-info/top_level.txt
google_maps_reviews-0.0.3.dist-info/RECORD
