Metadata-Version: 2.1
Name: google-maps-reviews
Version: 0.0.3
Summary: Google Maps Reviews API SDK
Home-page: https://github.com/outscraper/google-maps-reviews-python
Author: Outscraper
Author-email: developers@outscraper.com
License: MIT
Keywords: google maps reviews api sdk scraper parser
Platform: UNKNOWN
Classifier: Programming Language :: Python
Classifier: License :: OSI Approved :: MIT License
Classifier: Operating System :: OS Independent
Classifier: Intended Audience :: Developers
Classifier: Topic :: Utilities
License-File: LICENSE
Requires-Dist: requests
